src/app.py
src/liyedong_fastapi_demo/__init__.py
src/liyedong_fastapi_demo/cmdline.py
src/liyedong_fastapi_demo/config/__init__.py
src/liyedong_fastapi_demo/config/settings.local.yml
src/liyedong_fastapi_demo/config/settings.yml
src/liyedong_fastapi_demo/dao.py
src/liyedong_fastapi_demo/db.py
src/liyedong_fastapi_demo/dependencies.py
src/liyedong_fastapi_demo/log.py
src/liyedong_fastapi_demo/middlewares.py
src/liyedong_fastapi_demo/migration/__init__.py
src/liyedong_fastapi_demo/migration/alembic.ini
src/liyedong_fastapi_demo/migration/env.py
src/liyedong_fastapi_demo/migration/README
src/liyedong_fastapi_demo/migration/script.py.mako
src/liyedong_fastapi_demo/migration/versions/5ff0288db228_init.py
src/liyedong_fastapi_demo/migration/versions/9a65c40d318e_init.py
src/liyedong_fastapi_demo/migration/versions/__init__.py
src/liyedong_fastapi_demo/migration/versions/cb6d9a7d9420_init.py
src/liyedong_fastapi_demo/migration/versions/cbd3d9305678_init.py
src/liyedong_fastapi_demo/migration/versions/f1f23b0b267b_init_table.py
src/liyedong_fastapi_demo/models.py
src/liyedong_fastapi_demo/routes.py
src/liyedong_fastapi_demo/schemas.py
src/liyedong_fastapi_demo/server.py
src/liyedong_fastapi_demo/services.py
src/liyedong_fastapi_demo/utils.py
src/liyedong_fastapi_demo/views.py
src/tests/__init__.py
src/tests/conftest.py
src/tests/settings.yml
src/tests/test_cmdline.py
src/tests/test_dao.py
src/tests/test_dependencies.py
src/tests/test_services.py
src/tests/test_utils.py
src/tests/test_views.py
liyedong_fastapi_demo-0.1.0.dist-info/entry_points.txt
liyedong_fastapi_demo-0.1.0.dist-info/METADATA
liyedong_fastapi_demo-0.1.0.dist-info/WHEEL
liyedong_fastapi_demo-0.1.0.dist-info/RECORD
